mirinae/__init__.py
mirinae/config.py
mirinae/healthcheck.py
mirinae/mirinae.py
mirinae/version.py
mirinae/auth/__init__.py
mirinae/auth/header.py
mirinae/auth/refresh_token.py
mirinae/core/__init__.py
mirinae/core/mydata.py
mirinae/dashboard/__init__.py
mirinae/dashboard/dashboard.py
mirinae/dashboard/subtitle_generation.py
mirinae/dashboard/voice_separation.py
mirinae/flow/__init__.py
mirinae/flow/run.py
mirinae/folder/__init__.py
mirinae/folder/create.py
mirinae/folder/delete.py
mirinae/folder/doc.py
mirinae/folder/folder.py
mirinae/folder/info.py
mirinae/folder/move.py
mirinae/folder/update.py
mirinae/parsers/__init__.py
mirinae/parsers/common.py
mirinae/parsers/flow.py
mirinae/parsers/load.py
mirinae/parsers/product.py
mirinae/parsers/project.py
mirinae/parsers/user.py
mirinae/product/__init__.py
mirinae/product/create.py
mirinae/product/delete.py
mirinae/product/get.py
mirinae/product/update.py
mirinae/project/__init__.py
mirinae/project/copy.py
mirinae/project/create.py
mirinae/project/delete.py
mirinae/project/get.py
mirinae/project/update.py
mirinae/projects/__init__.py
mirinae/projects/proejcts.py
mirinae/user/__init__.py
mirinae/user/delete.py
mirinae/user/login.py
mirinae/user/logout.py
mirinae/user/refresh.py
mirinae/user/signup.py
mirinae/user/subscription.py
mirinae/user/update.py
mirinae/utils/__init__.py
mirinae/utils/naming.py
mirinae/utils/parameters.py
mirinae/utils/set_logging.py
mirinae/utils/show.py
mirinae/utils/spinner.py
mirinae-0.1.16.dist-info/METADATA
mirinae-0.1.16.dist-info/WHEEL
mirinae-0.1.16.dist-info/entry_points.txt
mirinae-0.1.16.dist-info/top_level.txt
mirinae-0.1.16.dist-info/RECORD
