Metadata-Version: 2.1
Name: mirinae
Version: 0.1.16
Summary: Mirinae is a Python package for MAGO's framework
Home-page: https://github.com/holamago/mirinae-cli.git
Author: MAGO
Author-email: galois@holamago.com
License: MIT
Requires-Python: >=3.9
Requires-Dist: requests
Requires-Dist: type_docopt
Requires-Dist: pydantic
Requires-Dist: pandas
Requires-Dist: matplotlib
Requires-Dist: networkx
